MANIFEST.in
README.md
REST-APIs.md
changelog.md
roadmap.md
setup.cfg
setup.py
pypot/__init__.py
pypot/_version.py
pypot/kinematics.py
pypot/creatures/__init__.py
pypot/creatures/abstractcreature.py
pypot/creatures/configure_utility.py
pypot/creatures/ik.py
pypot/creatures/services_launcher.py
pypot/dynamixel/__init__.py
pypot/dynamixel/controller.py
pypot/dynamixel/conversion.py
pypot/dynamixel/error.py
pypot/dynamixel/motor.py
pypot/dynamixel/syncloop.py
pypot/dynamixel/io/__init__.py
pypot/dynamixel/io/abstract_io.py
pypot/dynamixel/io/io.py
pypot/dynamixel/io/io_320.py
pypot/dynamixel/protocol/__init__.py
pypot/dynamixel/protocol/v1.py
pypot/dynamixel/protocol/v2.py
pypot/primitive/__init__.py
pypot/primitive/manager.py
pypot/primitive/move.py
pypot/primitive/primitive.py
pypot/primitive/utils.py
pypot/robot/__init__.py
pypot/robot/config.py
pypot/robot/controller.py
pypot/robot/io.py
pypot/robot/motor.py
pypot/robot/remote.py
pypot/robot/robot.py
pypot/robot/sensor.py
pypot/sensor/__init__.py
pypot/sensor/optibridge.py
pypot/sensor/optitrack.py
pypot/sensor/arduino/__init__.py
pypot/sensor/arduino/arduino_sensor.py
pypot/sensor/camera/__init__.py
pypot/sensor/camera/abstractcam.py
pypot/sensor/camera/dummy.py
pypot/sensor/camera/opencvcam.py
pypot/sensor/contact/__init__.py
pypot/sensor/contact/contact.py
pypot/sensor/depth/__init__.py
pypot/sensor/depth/sonar.py
pypot/sensor/imagefeature/__init__.py
pypot/sensor/imagefeature/blob.py
pypot/sensor/imagefeature/face.py
pypot/sensor/imagefeature/marker.py
pypot/sensor/kinect/__init__.py
pypot/sensor/kinect/sensor.py
pypot/server/__init__.py
pypot/server/httpserver.py
pypot/server/rest.py
pypot/server/server.py
pypot/server/snap.py
pypot/server/ws.py
pypot/server/zmqserver.py
pypot/server/snap_projects/poppy-base_demo_FR.xml
pypot/server/snap_projects/poppy-demo-project.xml
pypot/server/snap_projects/pypot-snap-blocks.xml
pypot/server/snap_projects/roboticia_basic_blocks_en.xml
pypoticia.egg-info/PKG-INFO
pypoticia.egg-info/SOURCES.txt
pypoticia.egg-info/dependency_links.txt
pypoticia.egg-info/entry_points.txt
pypoticia.egg-info/not-zip-safe
pypoticia.egg-info/requires.txt
pypoticia.egg-info/top_level.txt