Metadata-Version: 1.1
Name: pypoticia
Version: 3.2.0
Summary: Python Library for Robot Control
Home-page: https://github.com/poppy-project/pypot
Author: See https://github.com/poppy-project/pypot/graphs/contributors
Author-email: pierre.rouanet@gmail.com
License: GNU GENERAL PUBLIC LICENSE Version 3
Platform: UNKNOWN
Classifier: Programming Language :: Python :: 2
Classifier: Programming Language :: Python :: 3
Classifier: Topic :: Scientific/Engineering
